a_pandas_ex_obj_into_cell/LICENSE
a_pandas_ex_obj_into_cell/README.MD
a_pandas_ex_obj_into_cell/__init__.py
a_pandas_ex_obj_into_cell/requirements.txt
a_pandas_ex_obj_into_cell/thirdparty.json
a_pandas_ex_obj_into_cell-0.12.dist-info/LICENSE.rst
a_pandas_ex_obj_into_cell-0.12.dist-info/METADATA
a_pandas_ex_obj_into_cell-0.12.dist-info/WHEEL
a_pandas_ex_obj_into_cell-0.12.dist-info/top_level.txt
a_pandas_ex_obj_into_cell-0.12.dist-info/RECORD
